etm2human.py
etm2trace.py
rpmsgtrace2pcap.py
traceparse.py
gdbrpc/.gitignore
gdbrpc/README.md
gdbrpc/__init__.py
gdbrpc/__main__.py
gdbrpc/cli.py
gdbrpc/client.py
gdbrpc/commands.py
gdbrpc/pyproject.toml
gdbrpc/server.py
gdbrpc/utils.py
gdbrpc/examples/breakpoint.py
gdbrpc/examples/examplescript.py
gdbrpc/examples/gdbscript.py
gdbrpc/examples/getheaps.py
gdbrpc/examples/memleak.py
gdbrpc/tests/stresstest.py
nxelf/__init__.py
nxelf/elf.py
nxelf/macros.py
nxgdb/__init__.py
nxgdb/armspunwind.py
nxgdb/autocompeletion.py
nxgdb/backtrace.py
nxgdb/circbuf.py
nxgdb/critmon.py
nxgdb/debug.py
nxgdb/diagnose.py
nxgdb/dmesg.py
nxgdb/elf.py
nxgdb/gcore.py
nxgdb/gdbrpc.py
nxgdb/irq.py
nxgdb/kasan.py
nxgdb/libuv.py
nxgdb/lists.py
nxgdb/memcheck.py
nxgdb/memclassify.py
nxgdb/memdump.py
nxgdb/memleak.py
nxgdb/mm.py
nxgdb/net.py
nxgdb/noteram.py
nxgdb/notesnap.py
nxgdb/pginfo.py
nxgdb/pm.py
nxgdb/prefix.py
nxgdb/profile.py
nxgdb/quickjs.py
nxgdb/rpmsg.py
nxgdb/rpmsgtrace2pcap.py
nxgdb/stack.py
nxgdb/target.py
nxgdb/thread.py
nxgdb/tlsdump.py
nxgdb/tricore.py
nxgdb/uname.py
nxgdb/uorb.py
nxgdb/utils.py
nxgdb/venv.py
nxgdb/wdog.py
nxgdb/wqueue.py
nxgdb/fs/__init__.py
nxgdb/fs/command.py
nxgdb/fs/fatfs.py
nxgdb/fs/fs.py
nxgdb/fs/inode.py
nxgdb/fs/littlefs.py
nxgdb/fs/lrofs.py
nxgdb/fs/romfs.py
nxgdb/fs/utils.py
nxgdb/fs/yaffs.py
nxgdb/memclassifier/default.py
nxgdb/memclassifier/size.py
nxgdb/memclassifier/utils.py
nxgdb/nxcrash/busyloop.py
nxgdb/nxcrash/deadlock.py
nxgdb/nxcrash/stackoverflow.py
nxgdb/nxcrash/thread.py
nxgdb/protocols/circbuf.py
nxgdb/protocols/fs.py
nxgdb/protocols/irq.py
nxgdb/protocols/mm.py
nxgdb/protocols/thread.py
nxgdb/protocols/uorb.py
nxgdb/protocols/value.py
nxgdb/protocols/wdog.py
nxgdb/protocols/wqueue.py
nxgdbmcp/__init__.py
nxgdbmcp/__main__.py
nxgdbmcp/diagnostic-agent.md
nxgdbmcp/gmcp/__init__.py
nxgdbmcp/gmcp/context.py
nxgdbmcp/gmcp/main.py
nxgdbmcp/gmcp/utils.py
nxgdbmcp/gmcp/session/__init__.py
nxgdbmcp/gmcp/session/context.py
pynuttx-0.0.7.dist-info/METADATA
pynuttx-0.0.7.dist-info/WHEEL
pynuttx-0.0.7.dist-info/entry_points.txt
pynuttx-0.0.7.dist-info/top_level.txt
pynuttx-0.0.7.dist-info/RECORD
